the_solitary_castle_in_the_mirror/__init__.py
the_solitary_castle_in_the_mirror/__main__.py
the_solitary_castle_in_the_mirror/_date.py
the_solitary_castle_in_the_mirror/_types.py
the_solitary_castle_in_the_mirror/core.py
kojo_fan_art-0.1.1.dist-info/LICENSE
kojo_fan_art-0.1.1.dist-info/METADATA
kojo_fan_art-0.1.1.dist-info/WHEEL
kojo_fan_art-0.1.1.dist-info/entry_points.txt
kojo_fan_art-0.1.1.dist-info/top_level.txt
kojo_fan_art-0.1.1.dist-info/RECORD
